puzzlekit/__init__.py
puzzlekit/core/__init__.py
puzzlekit/core/direction.py
puzzlekit/core/docs_template.py
puzzlekit/core/grid.py
puzzlekit/core/position.py
puzzlekit/core/puzzlink.py
puzzlekit/core/regionsgrid.py
puzzlekit/core/result.py
puzzlekit/core/solver.py
puzzlekit/parsers/__init__.py
puzzlekit/parsers/common.py
puzzlekit/parsers/registry.py
puzzlekit/solvers/__init__.py
puzzlekit/solvers/abc_end_view.py
puzzlekit/solvers/akari.py
puzzlekit/solvers/balance_loop.py
puzzlekit/solvers/battleship.py
puzzlekit/solvers/binairo.py
puzzlekit/solvers/bosanowa.py
puzzlekit/solvers/bricks.py
puzzlekit/solvers/buraitoraito.py
puzzlekit/solvers/butterfly_sudoku.py
puzzlekit/solvers/cave.py
puzzlekit/solvers/clueless_1_sudoku.py
puzzlekit/solvers/clueless_2_sudoku.py
puzzlekit/solvers/country_road.py
puzzlekit/solvers/creek.py
puzzlekit/solvers/detour.py
puzzlekit/solvers/diff_neighbors.py
puzzlekit/solvers/dominos.py
puzzlekit/solvers/dotchi_loop.py
puzzlekit/solvers/double_back.py
puzzlekit/solvers/entry_exit.py
puzzlekit/solvers/eulero.py
puzzlekit/solvers/even_odd_sudoku.py
puzzlekit/solvers/fobidoshi.py
puzzlekit/solvers/fuzuli.py
puzzlekit/solvers/gappy.py
puzzlekit/solvers/gattai_8_sudoku.py
puzzlekit/solvers/grand_tour.py
puzzlekit/solvers/hakoiri.py
puzzlekit/solvers/hakyuu.py
puzzlekit/solvers/heyawake.py
puzzlekit/solvers/hidoku.py
puzzlekit/solvers/hitori.py
puzzlekit/solvers/jigsaw_sudoku.py
puzzlekit/solvers/juosan.py
puzzlekit/solvers/kakkuru.py
puzzlekit/solvers/kakurasu.py
puzzlekit/solvers/kakuro.py
puzzlekit/solvers/ken_ken.py
puzzlekit/solvers/killer_sudoku.py
puzzlekit/solvers/koburin.py
puzzlekit/solvers/kuromasu.py
puzzlekit/solvers/kuroshuto.py
puzzlekit/solvers/linesweeper.py
puzzlekit/solvers/lits.py
puzzlekit/solvers/magnetic.py
puzzlekit/solvers/makaro.py
puzzlekit/solvers/masyu.py
puzzlekit/solvers/mathrax.py
puzzlekit/solvers/minesweeper.py
puzzlekit/solvers/moon_sun.py
puzzlekit/solvers/mosaic.py
puzzlekit/solvers/munraito.py
puzzlekit-0.3.0.dist-info/licenses/LICENSE
puzzlekit-0.3.0.dist-info/METADATA
puzzlekit-0.3.0.dist-info/WHEEL
puzzlekit-0.3.0.dist-info/top_level.txt
puzzlekit-0.3.0.dist-info/RECORD
