Metadata-Version: 2.4
Name: puzzlekit
Version: 0.3.0
Summary: A comprehensive logic puzzle solver (70+) based on Google OR-Tools. e.g., solvers for Nonogram, Slitherlink, Akari, Yajilin, Hitori and Sudoku-variants.
Author-email: SmilingWayne <xiaoxiaowayne@gmail.com>
License: MIT License
Project-URL: Homepage, https://github.com/SmilingWayne/PuzzleSolver
Project-URL: Repository, https://github.com/SmilingWayne/PuzzleSolver
Project-URL: Issues, https://github.com/SmilingWayne/PuzzleSolver/issues
Keywords: puzzle,solver,logic,cp-sat,efficient,python,nonogram,slitherlink,yajilin,hitori,sudoku,akari
Classifier: Development Status :: 3 - Alpha
Classifier: Intended Audience :: Developers
Classifier: Intended Audience :: Science/Research
Classifier: License :: OSI Approved :: MIT License
Classifier: Programming Language :: Python :: 3
Classifier: Programming Language :: Python :: 3.10
Classifier: Programming Language :: Python :: 3.11
Classifier: Programming Language :: Python :: 3.12
Classifier: Topic :: Scientific/Engineering :: Artificial Intelligence
Classifier: Topic :: Games/Entertainment :: Puzzle Games
Classifier: Operating System :: OS Independent
Requires-Python: >=3.10
License-File: LICENSE
Requires-Dist: numpy
Requires-Dist: ortools>=9.6
Requires-Dist: matplotlib
Requires-Dist: typeguard
Dynamic: license-file
